README.md
setup.py
stylelens_sdk/__init__.py
stylelens_sdk/api_client.py
stylelens_sdk/configuration.py
stylelens_sdk/rest.py
stylelens_sdk.egg-info/PKG-INFO
stylelens_sdk.egg-info/SOURCES.txt
stylelens_sdk.egg-info/dependency_links.txt
stylelens_sdk.egg-info/requires.txt
stylelens_sdk.egg-info/top_level.txt
stylelens_sdk/apis/__init__.py
stylelens_sdk/apis/feed_api.py
stylelens_sdk/apis/object_api.py
stylelens_sdk/apis/product_api.py
stylelens_sdk/models/__init__.py
stylelens_sdk/models/box_array.py
stylelens_sdk/models/box_object.py
stylelens_sdk/models/boxes_array.py
stylelens_sdk/models/get_feed_response.py
stylelens_sdk/models/get_objects_response.py
stylelens_sdk/models/get_objects_response_data.py
stylelens_sdk/models/get_product_response.py
stylelens_sdk/models/get_products_response.py
stylelens_sdk/models/product.py
stylelens_sdk/models/products_array.py
stylelens_sdk/models/search_image_response.py
test/__init__.py
test/test_box_array.py
test/test_box_object.py
test/test_boxes_array.py
test/test_feed_api.py
test/test_get_feed_response.py
test/test_get_objects_response.py
test/test_get_objects_response_data.py
test/test_get_product_response.py
test/test_get_products_response.py
test/test_object_api.py
test/test_product.py
test/test_product_api.py
test/test_products_array.py
test/test_search_image_response.py