Metadata-Version: 1.0
Name: stylelens-sdk
Version: 1.0.6
Summary: style-api
Home-page: UNKNOWN
Author: UNKNOWN
Author-email: master@bluehack.net
License: UNKNOWN
Keywords: bluelens,stylelens
Platform: UNKNOWN
